calf/__init__.py
calf/__main__.py
calf/py.typed
calf-0.5.dist-info/METADATA
calf-0.5.dist-info/WHEEL
calf-0.5.dist-info/entry_points.txt
calf-0.5.dist-info/licenses/LICENSE
calf-0.5.dist-info/RECORD
