Metadata-Version: 2.4
Name: calf
Version: 0.5
Summary: Command Argument Loading Functions
Project-URL: Homepage, https://github.com/isaacto/calf
Project-URL: Repository, https://github.com/isaacto/calf.git
Project-URL: Issues, https://github.com/isaacto/calf/issues
Author-email: Isaac To <isaac.to@gmail.com>
License-Expression: MIT
License-File: LICENSE
Classifier: Development Status :: 4 - Beta
Classifier: Intended Audience :: Developers
Classifier: Operating System :: OS Independent
Classifier: Programming Language :: Python :: 3.9
Classifier: Programming Language :: Python :: 3.10
Classifier: Programming Language :: Python :: 3.11
Classifier: Programming Language :: Python :: 3.12
Classifier: Programming Language :: Python :: 3.13
Classifier: Programming Language :: Python :: 3.14
Classifier: Topic :: Software Development :: Libraries
Requires-Python: >=3.9
